[{"Type":"SoundCue","Name":"Explosion_SwiftStrike_Cue","Class":"UScriptClass'SoundCue'","Properties":{"FirstNode":{"ObjectName":"SoundNodeModulator'Explosion_SwiftStrike_Cue:SoundNodeModulator_20'","ObjectPath":"WorldExplorers/Content/Audio/Combat/Explosion_SwiftStrike_Cue.1"},"VolumeMultiplier":1.0,"SoundClassObject":{"ObjectName":"SoundClass'Generic_Combat_Sounds'","ObjectPath":"WorldExplorers/Content/Audio/SoundClasses/Generic_Combat_Sounds.0"},"ConcurrencySet":[{"ObjectName":"SoundConcurrency'CNC_Combat_MultiHit'","ObjectPath":"WorldExplorers/Content/Audio/UI/CNC_Combat_MultiHit.0"}],"ConcurrencyOverrides":{"MaxCount":1,"ResolutionRule":"EMaxConcurrentResolutionRule::PreventNew"},"Duration":1.5290625,"MaxDistance":2097152.0}},{"Type":"SoundNodeModulator","Name":"SoundNodeModulator_20","Outer":"Explosion_SwiftStrike_Cue","Class":"UScriptClass'SoundNodeModulator'","Properties":{"PitchMin":1.0,"PitchMax":1.2,"ChildNodes":[{"ObjectName":"SoundNodeWavePlayer'Explosion_SwiftStrike_Cue:SoundNodeWavePlayer_5'","ObjectPath":"WorldExplorers/Content/Audio/Combat/Explosion_SwiftStrike_Cue.2"}]}},{"Type":"SoundNodeWavePlayer","Name":"SoundNodeWavePlayer_5","Outer":"Explosion_SwiftStrike_Cue","Class":"UScriptClass'SoundNodeWavePlayer'","Properties":{"SoundWaveAssetPtr":{"AssetPathName":"/Game/Audio/Combat/strike_explo_01.strike_explo_01","SubPathString":""}},"SoundWave":{"ObjectName":"SoundWave'strike_explo_01'","ObjectPath":"WorldExplorers/Content/Audio/Combat/strike_explo_01.0"}}]