[{"Type":"SoundWave","Name":"car_stop_moving","Class":"UScriptClass'SoundWave'","Properties":{"NumChannels":1,"SampleRate":22050,"bOverrideConcurrency":true,"ConcurrencyOverrides":{"ResolutionRule":"EMaxConcurrentResolutionRule::PreventNew"},"Duration":2.6530159},"CompressedFormatData":{"OGG10000-1-1-1-1-1":{"BulkDataFlags":"BULKDATA_SingleUse | BULKDATA_ForceInlinePayload","ElementCount":16238,"SizeOnDisk":16238,"OffsetInFile":"0x4944"}},"RawData":null,"CompressedDataGuid":"43088FF4-4A0863BA-3BB921B0-3903F7D6","RunningPlatformData":null}]