[{"Type":"BodySetup","Name":"BodySetup_0","Outer":"S_QuickTime_Button_Gem_UP_New","Class":"UScriptClass'BodySetup'","Properties":{"DefaultInstance":{"ObjectType":"ECC_WorldStatic","CollisionProfileName":"BlockAll"}},"BodySetupGuid":"C7629C8D4650E29AD237D7ACDF3736F2","CookedFormatData":{"PhysXPC":{"BulkDataFlags":"BULKDATA_SingleUse | BULKDATA_ForceInlinePayload","ElementCount":9077,"SizeOnDisk":9077,"OffsetInFile":"0x585E"}}},{"Type":"NavCollision","Name":"NavCollision_0","Outer":"S_QuickTime_Button_Gem_UP_New","Class":"UScriptClass'NavCollision'","CookedFormatData":{"NavCollision_X":{"BulkDataFlags":"BULKDATA_SingleUse | BULKDATA_ForceInlinePayload","ElementCount":21,"SizeOnDisk":21,"OffsetInFile":"0x7C1B"}}},{"Type":"StaticMesh","Name":"S_QuickTime_Button_Gem_UP_New","Class":"UScriptClass'StaticMesh'","Properties":{"StaticMaterials":[{"MaterialInterface":{"ObjectName":"Material'M_QTE_Button_NEW'","ObjectPath":"WorldExplorers/Content/HUD/QuickTimeEvents/M_QTE_Button_NEW.0"},"MaterialSlotName":"lambert4SG","ImportedMaterialSlotName":"lambert4SG","UVChannelData":{"bInitialized":true,"bOverrideDensities":false,"LocalUVDensities":0.0}}],"LightmapUVDensity":83.661316,"LightMapResolution":64,"LightMapCoordinateIndex":1,"ExtendedBounds":{"Origin":{"X":-1.7514954,"Y":-4.2031097,"Z":1.8172615},"BoxExtent":{"X":40.493427,"Y":41.827393,"Z":5.364418e-7},"SphereRadius":42.402412}},"BodySetup":{"ObjectName":"BodySetup'S_QuickTime_Button_Gem_UP_New:BodySetup_0'","ObjectPath":"WorldExplorers/Content/HUD/QuickTimeEvents/S_QuickTime_Button_Gem_UP_New.0"},"NavCollision":{"ObjectName":"NavCollision'S_QuickTime_Button_Gem_UP_New:NavCollision_0'","ObjectPath":"WorldExplorers/Content/HUD/QuickTimeEvents/S_QuickTime_Button_Gem_UP_New.1"},"LightingGuid":"AF1E8300-4454EF75-C17A9694-C96301D1","RenderData":{"LODs":[{"Sections":[{"MaterialIndex":0,"FirstIndex":0,"NumTriangles":100,"MinVertexIndex":0,"MaxVertexIndex":100,"bEnableCollision":true,"bCastShadow":true,"bForceOpaque":false,"bVisibleInRayTracing":true}],"MaxDeviation":0.0,"PositionVertexBuffer":{"Stride":12,"NumVertices":101},"VertexBuffer":{"NumTexCoords":2,"NumVertices":101,"Strides":-1,"UseHighPrecisionTangentBasis":false,"UseFullPrecisionUVs":false},"ColorVertexBuffer":{"Stride":0,"NumVertices":0}}],"Bounds":{"Origin":{"X":-1.7514954,"Y":-4.2031097,"Z":1.8172615},"BoxExtent":{"X":40.493427,"Y":41.827393,"Z":5.364418e-7},"SphereRadius":42.402412},"bLODsShareStaticLighting":true,"ScreenSize":[1.0,0.0,0.0,0.0,0.0,0.0,0.0,0.0]}}]