[{"Type":"BlueprintGeneratedClass","Name":"Passive_ThunderGod_T02_C","Super":"Passive_ThunderGod_T01_C","Class":"UScriptClass'BlueprintGeneratedClass'","Properties":{"SimpleConstructionScript":{"ObjectName":"SimpleConstructionScript'Passive_ThunderGod_T02_C:SimpleConstructionScript_0'","ObjectPath":"WorldExplorers/Content/Skills/PassiveSkills/Passive_ThunderGod_T02.5"},"InheritableComponentHandler":{"ObjectName":"InheritableComponentHandler'Passive_ThunderGod_T02_C:InheritableComponentHandler'","ObjectPath":"WorldExplorers/Content/Skills/PassiveSkills/Passive_ThunderGod_T02.2"}},"SuperStruct":{"ObjectName":"BlueprintGeneratedClass'Passive_ThunderGod_T01_C'","ObjectPath":"WorldExplorers/Content/Skills/PassiveSkills/Passive_ThunderGod_T01.1"},"ClassFlags":8652820,"ClassWithin":{"ObjectName":"Class'Object'","ObjectPath":"/Script/CoreUObject"},"ClassConfigName":"Engine","bCooked":true,"ClassDefaultObject":{"ObjectName":"Passive_ThunderGod_T02_C'Default__Passive_ThunderGod_T02_C'","ObjectPath":"WorldExplorers/Content/Skills/PassiveSkills/Passive_ThunderGod_T02.1"}},{"Type":"Passive_ThunderGod_T02_C","Name":"Default__Passive_ThunderGod_T02_C","Template":"Default__Passive_ThunderGod_T01_C","Class":"BlueprintGeneratedClass'WorldExplorers/Content/Skills/PassiveSkills/Passive_ThunderGod_T02.Passive_ThunderGod_T02_C'","Properties":{"AbilityLookupName":"ThunderGod.T02","DisplayName":{"Namespace":"","Key":"5988E71C436D91A0F4E57B91403A6ECC","SourceString":"Thunder God II","LocalizedString":"Thunder God II"},"DebugName":"Passive_ThunderGod_T02"}},{"Type":"InheritableComponentHandler","Name":"InheritableComponentHandler","Outer":"Passive_ThunderGod_T02_C","Class":"UScriptClass'InheritableComponentHandler'"},{"Type":"SceneComponent","Name":"DefaultSceneRoot_GEN_VARIABLE","Outer":"Passive_ThunderGod_T02_C","Class":"UScriptClass'SceneComponent'"},{"Type":"SCS_Node","Name":"SCS_Node_0","Outer":"SimpleConstructionScript_0","Class":"UScriptClass'SCS_Node'","Properties":{"ComponentClass":{"ObjectName":"Class'SceneComponent'","ObjectPath":"/Script/Engine"},"ComponentTemplate":{"ObjectName":"SceneComponent'Passive_ThunderGod_T02_C:DefaultSceneRoot_GEN_VARIABLE'","ObjectPath":"WorldExplorers/Content/Skills/PassiveSkills/Passive_ThunderGod_T02.3"},"VariableGuid":"299CB09F-43D925CF-CE9B4EAF-C6A02B97","InternalVariableName":"DefaultSceneRoot"}},{"Type":"SimpleConstructionScript","Name":"SimpleConstructionScript_0","Outer":"Passive_ThunderGod_T02_C","Class":"UScriptClass'SimpleConstructionScript'","Properties":{"DefaultSceneRootNode":{"ObjectName":"SCS_Node'Passive_ThunderGod_T02_C:SimpleConstructionScript_0.SCS_Node_0'","ObjectPath":"WorldExplorers/Content/Skills/PassiveSkills/Passive_ThunderGod_T02.4"}}}]