[{"Type":"BlueprintGeneratedClass","Name":"Passive_FireFighter_T03_C","Super":"Passive_FireFighter_T01_C","Class":"UScriptClass'BlueprintGeneratedClass'","Properties":{"SimpleConstructionScript":{"ObjectName":"SimpleConstructionScript'Passive_FireFighter_T03_C:SimpleConstructionScript_0'","ObjectPath":"WorldExplorers/Content/Skills/PassiveSkills/Passive_FireFighter_T03.5"},"InheritableComponentHandler":{"ObjectName":"InheritableComponentHandler'Passive_FireFighter_T03_C:InheritableComponentHandler'","ObjectPath":"WorldExplorers/Content/Skills/PassiveSkills/Passive_FireFighter_T03.2"}},"SuperStruct":{"ObjectName":"BlueprintGeneratedClass'Passive_FireFighter_T01_C'","ObjectPath":"WorldExplorers/Content/Skills/PassiveSkills/Passive_FireFighter_T01.1"},"ClassFlags":8652820,"ClassWithin":{"ObjectName":"Class'Object'","ObjectPath":"/Script/CoreUObject"},"ClassConfigName":"Engine","bCooked":true,"ClassDefaultObject":{"ObjectName":"Passive_FireFighter_T03_C'Default__Passive_FireFighter_T03_C'","ObjectPath":"WorldExplorers/Content/Skills/PassiveSkills/Passive_FireFighter_T03.1"}},{"Type":"Passive_FireFighter_T03_C","Name":"Default__Passive_FireFighter_T03_C","Template":"Default__Passive_FireFighter_T01_C","Class":"BlueprintGeneratedClass'WorldExplorers/Content/Skills/PassiveSkills/Passive_FireFighter_T03.Passive_FireFighter_T03_C'","Properties":{"AbilityLookupName":"FireFighter.T03","DisplayName":{"Namespace":"","Key":"31F409F74EA41490806DC483E31A0BD5","SourceString":"Fire Fighter III","LocalizedString":"Fire Fighter III"}}},{"Type":"InheritableComponentHandler","Name":"InheritableComponentHandler","Outer":"Passive_FireFighter_T03_C","Class":"UScriptClass'InheritableComponentHandler'"},{"Type":"SceneComponent","Name":"DefaultSceneRoot_GEN_VARIABLE","Outer":"Passive_FireFighter_T03_C","Class":"UScriptClass'SceneComponent'"},{"Type":"SCS_Node","Name":"SCS_Node_0","Outer":"SimpleConstructionScript_0","Class":"UScriptClass'SCS_Node'","Properties":{"ComponentClass":{"ObjectName":"Class'SceneComponent'","ObjectPath":"/Script/Engine"},"ComponentTemplate":{"ObjectName":"SceneComponent'Passive_FireFighter_T03_C:DefaultSceneRoot_GEN_VARIABLE'","ObjectPath":"WorldExplorers/Content/Skills/PassiveSkills/Passive_FireFighter_T03.3"},"VariableGuid":"2B9EC6F6-46F1E6F0-1FE1B3BE-75D53C56","InternalVariableName":"DefaultSceneRoot"}},{"Type":"SimpleConstructionScript","Name":"SimpleConstructionScript_0","Outer":"Passive_FireFighter_T03_C","Class":"UScriptClass'SimpleConstructionScript'","Properties":{"DefaultSceneRootNode":{"ObjectName":"SCS_Node'Passive_FireFighter_T03_C:SimpleConstructionScript_0.SCS_Node_0'","ObjectPath":"WorldExplorers/Content/Skills/PassiveSkills/Passive_FireFighter_T03.4"}}}]