[{"Type":"ObjectProperty","Name":"DefaultSceneRoot","Outer":"DialogManager_BP_C","Class":"UScriptClass'ObjectProperty'","PropertyFlags":17180393476,"PropertyClass":{"ObjectName":"Class'SceneComponent'","ObjectPath":"/Script/Engine"}},{"Type":"BlueprintGeneratedClass","Name":"DialogManager_BP_C","Class":"UScriptClass'BlueprintGeneratedClass'","Properties":{"SimpleConstructionScript":{"ObjectName":"SimpleConstructionScript'DialogManager_BP_C:SimpleConstructionScript_0'","ObjectPath":"WorldExplorers/Content/Audio/Dialog/DialogManager_BP.5"}},"SuperStruct":{"ObjectName":"Class'WExpDialogManager'","ObjectPath":"/Script/WorldExplorers"},"Children":[{"ObjectName":"ObjectProperty'DialogManager_BP_C:DefaultSceneRoot'","ObjectPath":"WorldExplorers/Content/Audio/Dialog/DialogManager_BP.0"}],"ClassFlags":8652820,"ClassWithin":{"ObjectName":"Class'Object'","ObjectPath":"/Script/CoreUObject"},"ClassConfigName":"Engine","bCooked":true,"ClassDefaultObject":{"ObjectName":"DialogManager_BP_C'Default__DialogManager_BP_C'","ObjectPath":"WorldExplorers/Content/Audio/Dialog/DialogManager_BP.2"}},{"Type":"DialogManager_BP_C","Name":"Default__DialogManager_BP_C","Class":"BlueprintGeneratedClass'WorldExplorers/Content/Audio/Dialog/DialogManager_BP.DialogManager_BP_C'","Properties":{"DialogEvents":[{"Handle":{"DialogBank":null,"EventName":"Dummy_DO_NOT_USE","bReadOnly":true,"bBankDefined":false},"ChanceToPlay":1.0,"MinReplayTime":0.0,"MaxWitnessDistance":5000.0,"bInterruptCurrentLine":true,"bCanBeInterrupted":true,"bCanQue":true,"ContextSelectionMethod":"EWExpDialogSelectionMethod::Instigator","DialogDelay":0.0,"TimeLastPlayed":4.5916e-41}]}},{"Type":"SceneComponent","Name":"SceneComponent_0","Outer":"DialogManager_BP_C","Class":"UScriptClass'SceneComponent'"},{"Type":"SCS_Node","Name":"SCS_Node_0","Outer":"SimpleConstructionScript_0","Class":"UScriptClass'SCS_Node'","Properties":{"ComponentClass":{"ObjectName":"Class'SceneComponent'","ObjectPath":"/Script/Engine"},"ComponentTemplate":{"ObjectName":"SceneComponent'DialogManager_BP_C:SceneComponent_0'","ObjectPath":"WorldExplorers/Content/Audio/Dialog/DialogManager_BP.3"},"VariableGuid":"56BC9799-C494E6E6-321D4295-7D5EB316","InternalVariableName":"DefaultSceneRoot"}},{"Type":"SimpleConstructionScript","Name":"SimpleConstructionScript_0","Outer":"DialogManager_BP_C","Class":"UScriptClass'SimpleConstructionScript'","Properties":{"RootNodes":[{"ObjectName":"SCS_Node'DialogManager_BP_C:SimpleConstructionScript_0.SCS_Node_0'","ObjectPath":"WorldExplorers/Content/Audio/Dialog/DialogManager_BP.4"}],"AllNodes":[{"ObjectName":"SCS_Node'DialogManager_BP_C:SimpleConstructionScript_0.SCS_Node_0'","ObjectPath":"WorldExplorers/Content/Audio/Dialog/DialogManager_BP.4"}],"DefaultSceneRootNode":{"ObjectName":"SCS_Node'DialogManager_BP_C:SimpleConstructionScript_0.SCS_Node_0'","ObjectPath":"WorldExplorers/Content/Audio/Dialog/DialogManager_BP.4"}}}]