[{"Type":"SoundWave","Name":"warrior_f_NotReady_03","Class":"UScriptClass'SoundWave'","Properties":{"NumChannels":1,"SampleRate":22050,"bOverrideConcurrency":true,"ConcurrencyOverrides":{"ResolutionRule":"EMaxConcurrentResolutionRule::PreventNew"},"Duration":1.1658957},"CompressedFormatData":{"OGG10000-1-1-1-1-1":{"BulkDataFlags":"BULKDATA_SingleUse | BULKDATA_ForceInlinePayload","ElementCount":8259,"SizeOnDisk":8259,"OffsetInFile":"0x2A51"}},"RawData":null,"CompressedDataGuid":"F40E09E1-40B407CD-AA20C48D-F62C9634","RunningPlatformData":null}]