[{"Type":"SoundClass","Name":"UI","Class":"UScriptClass'SoundClass'","Properties":{"Properties":{"bIsUISound":true},"ChildClasses":[{"ObjectName":"SoundClass'UI_No_Ducking'","ObjectPath":"WorldExplorers/Content/Audio/SoundClasses/UI_No_Ducking.0"}],"PassiveSoundMixModifiers":[{"SoundMix":{"ObjectName":"SoundMix'WEXP_Duck_Music_Lightly'","ObjectPath":"WorldExplorers/Content/Audio/SoundClasses/WEXP_Duck_Music_Lightly.0"},"MinVolumeThreshold":0.0,"MaxVolumeThreshold":10.0}],"ParentClass":{"ObjectName":"SoundClass'SFX'","ObjectPath":"WorldExplorers/Content/Audio/SoundClasses/SFX.0"}}}]