[{"Type":"MorphTarget","Name":"body_bp","Outer":"SK_Shadowknight_VR2_Dark_Confuse_T05","Class":"UScriptClass'MorphTarget'","Properties":{"BaseSkelMesh":{"ObjectName":"SkeletalMesh'SK_Shadowknight_VR2_Dark_Confuse_T05'","ObjectPath":"WorldExplorers/Content/Characters/Classes/Shadowknight/Dark_Confuse/SK_Shadowknight_VR2_Dark_Confuse_T05.2"}},"MorphLODModels":[{"Vertices":[{"PositionDelta":{"X":-0.18446945,"Y":0.0,"Z":0.07110214},"TangentZDelta":{"X":-2.5617153e-10,"Y":0.0,"Z":1.2600998e-10},"SourceIdx":98},{"PositionDelta":{"X":0.15739202,"Y":0.0,"Z":0.00034332275},"TangentZDelta":{"X":4.8609117e-11,"Y":0.0,"Z":7.9103657e-10},"SourceIdx":111},{"PositionDelta":{"X":0.15947723,"Y":0.0,"Z":0.000289917},"TangentZDelta":{"X":0.0,"Y":0.0,"Z":0.0},"SourceIdx":112},{"PositionDelta":{"X":0.6101494,"Y":0.0,"Z":0.011817932},"TangentZDelta":{"X":0.0,"Y":0.0,"Z":0.0},"SourceIdx":113},{"PositionDelta":{"X":0.16394567,"Y":0.0,"Z":0.0},"TangentZDelta":{"X":0.0,"Y":0.0,"Z":0.0},"SourceIdx":114},{"PositionDelta":{"X":0.7086234,"Y":0.0,"Z":0.0},"TangentZDelta":{"X":0.0,"Y":0.0,"Z":0.0},"SourceIdx":118},{"PositionDelta":{"X":0.16180182,"Y":0.0,"Z":0.0},"TangentZDelta":{"X":0.0,"Y":0.0,"Z":0.0},"SourceIdx":120},{"PositionDelta":{"X":0.16259146,"Y":0.0,"Z":0.0},"TangentZDelta":{"X":0.0,"Y":0.0,"Z":0.0},"SourceIdx":122},{"PositionDelta":{"X":0.8829222,"Y":0.0,"Z":0.0},"TangentZDelta":{"X":0.0,"Y":0.0,"Z":0.0},"SourceIdx":123},{"PositionDelta":{"X":0.26067162,"Y":0.0,"Z":0.0},"TangentZDelta":{"X":0.0,"Y":0.0,"Z":0.0},"SourceIdx":125},{"PositionDelta":{"X":0.5090275,"Y":0.0,"Z":0.037704468},"TangentZDelta":{"X":-3.8751713e-10,"Y":0.0,"Z":7.775265e-10},"SourceIdx":126},{"PositionDelta":{"X":0.39745522,"Y":0.0,"Z":0.0},"TangentZDelta":{"X":-2.700089e-10,"Y":0.0,"Z":5.991474e-10},"SourceIdx":127},{"PositionDelta":{"X":0.07352209,"Y":0.0,"Z":0.0053482056},"TangentZDelta":{"X":-6.354268e-10,"Y":0.0,"Z":1.2816193e-9},"SourceIdx":128},{"PositionDelta":{"X":0.5209203,"Y":0.0,"Z":-0.076431274},"TangentZDelta":{"X":-1.872059e-10,"Y":0.0,"Z":6.3628747e-10},"SourceIdx":130},{"PositionDelta":{"X":0.40120697,"Y":0.0,"Z":-0.0029525757},"TangentZDelta":{"X":-1.119016e-10,"Y":0.0,"Z":-1.243805e-10},"SourceIdx":131},{"PositionDelta":{"X":0.39866543,"Y":0.0,"Z":-0.00061035156},"TangentZDelta":{"X":-1.462741e-11,"Y":0.0,"Z":-2.1222135e-11},"SourceIdx":132},{"PositionDelta":{"X":0.3991928,"Y":0.0,"Z":-0.0010986328},"TangentZDelta":{"X":-1.2540369e-10,"Y":0.0,"Z":-8.7572616e-11},"SourceIdx":133},{"PositionDelta":{"X":0.39836025,"Y":0.0,"Z":-0.00032806396},"TangentZDelta":{"X":3.718572e-10,"Y":0.0,"Z":1.0131984e-10},"SourceIdx":134},{"PositionDelta":{"X":0.39947605,"Y":0.0,"Z":-0.0013580322},"TangentZDelta":{"X":4.6370463e-10,"Y":-5.9604645e-8,"Z":1.5096546e-10},"SourceIdx":135},{"PositionDelta":{"X":0.39848137,"Y":0.0,"Z":-0.00044250488},"TangentZDelta":{"X":0.0,"Y":0.0,"Z":0.0},"SourceIdx":136},{"PositionDelta":{"X":0.39861107,"Y":0.0,"Z":-0.0005569458},"TangentZDelta":{"X":0.0,"Y":0.0,"Z":0.0},"SourceIdx":137},{"PositionDelta":{"X":0.3987627,"Y":0.0,"Z":-0.0007019043},"TangentZDelta":{"X":-2.53209e-10,"Y":0.0,"Z":2.2345148e-10},"SourceIdx":138},{"PositionDelta":{"X":0.39757633,"Y":0.0,"Z":0.00038909912},"TangentZDelta":{"X":-2.6010838e-10,"Y":0.0,"Z":2.3092284e-10},"SourceIdx":139},{"PositionDelta":{"X":0.39895916,"Y":0.0,"Z":-0.0008773804},"TangentZDelta":{"X":-1.6409896e-10,"Y":0.0,"Z":1.9311663e-10},"SourceIdx":140},{"PositionDelta":{"X":0.39800262,"Y":0.0,"Z":0.0},"TangentZDelta":{"X":0.0,"Y":0.0,"Z":0.0},"SourceIdx":141},{"PositionDelta":{"X":0.39607143,"Y":0.0,"Z":0.0},"TangentZDelta":{"X":-2.2908875e-10,"Y":-5.9604645e-8,"Z":3.0926373e-10},"SourceIdx":142},{"PositionDelta":{"X":0.39636707,"Y":0.0,"Z":0.0},"TangentZDelta":{"X":9.7502895e-11,"Y":0.0,"Z":3.7242032e-10},"SourceIdx":143},{"PositionDelta":{"X":0.2620361,"Y":0.0,"Z":0.0},"TangentZDelta":{"X":6.4416934e-9,"Y":0.0,"Z":-2.4772078e-9},"SourceIdx":144},{"PositionDelta":{"X":0.7223933,"Y":0.0,"Z":-0.0012741089},"TangentZDelta":{"X":3.5996628e-10,"Y":0.0,"Z":-4.266223e-10},"SourceIdx":145},{"PositionDelta":{"X":0.01597929,"Y":0.0,"Z":0.0},"TangentZDelta":{"X":1.0389442e-8,"Y":0.0,"Z":-7.470707e-9},"SourceIdx":146},{"PositionDelta":{"X":0.26125145,"Y":0.0,"Z":0.0},"TangentZDelta":{"X":-5.3362434e-9,"Y":0.0,"Z":1.1102014e-8},"SourceIdx":149},{"PositionDelta":{"X":0.02320671,"Y":0.0,"Z":0.0},"TangentZDelta":{"X":-1.7298618e-8,"Y":0.0,"Z":3.6918955e-8},"SourceIdx":150},{"PositionDelta":{"X":0.03349924,"Y":0.0,"Z":0.0},"TangentZDelta":{"X":-9.101626e-9,"Y":0.0,"Z":1.9150573e-8},"SourceIdx":151},{"PositionDelta":{"X":0.50294995,"Y":0.0,"Z":0.0},"TangentZDelta":{"X":1.0616876e-9,"Y":0.0,"Z":-4.2976467e-10},"SourceIdx":152},{"PositionDelta":{"X":0.018553734,"Y":0.0,"Z":0.0},"TangentZDelta":{"X":-1.4667121e-9,"Y":0.0,"Z":1.6686457e-9},"SourceIdx":153},{"PositionDelta":{"X":0.059402466,"Y":0.0,"Z":0.0},"TangentZDelta":{"X":8.2420737e-10,"Y":0.0,"Z":-4.533689e-10},"SourceIdx":154},{"PositionDelta":{"X":0.15075111,"Y":0.0,"Z":0.0},"TangentZDelta":{"X":7.742358e-10,"Y":0.0,"Z":-9.861445e-11},"SourceIdx":156},{"PositionDelta":{"X":0.5047817,"Y":0.0,"Z":0.0},"TangentZDelta":{"X":8.6968344e-10,"Y":0.0,"Z":-1.6498802e-11},"SourceIdx":173},{"PositionDelta":{"X":0.14496613,"Y":0.0,"Z":0.0},"TangentZDelta":{"X":0.0,"Y":0.0,"Z":0.0},"SourceIdx":174},{"PositionDelta":{"X":0.069093704,"Y":0.0,"Z":0.0},"TangentZDelta":{"X":-1.5666224e-9,"Y":0.0,"Z":-7.313872e-9},"SourceIdx":175},{"PositionDelta":{"X":0.03697014,"Y":0.0,"Z":0.0},"TangentZDelta":{"X":0.0,"Y":0.0,"Z":0.0},"SourceIdx":206},{"PositionDelta":{"X":0.038734436,"Y":0.0,"Z":0.0},"TangentZDelta":{"X":3.3074699e-9,"Y":0.0,"Z":-5.847454e-9},"SourceIdx":208},{"PositionDelta":{"X":0.020300865,"Y":0.0,"Z":0.0},"TangentZDelta":{"X":0.0,"Y":0.0,"Z":0.0},"SourceIdx":209},{"PositionDelta":{"X":0.04669571,"Y":0.0,"Z":0.0},"TangentZDelta":{"X":-2.9033949e-9,"Y":0.0,"Z":1.6013315e-9},"SourceIdx":212},{"PositionDelta":{"X":0.34230328,"Y":0.0,"Z":0.0},"TangentZDelta":{"X":-2.1893065e-9,"Y":0.0,"Z":2.3569866e-9},"SourceIdx":213},{"PositionDelta":{"X":0.06415081,"Y":0.0,"Z":0.0},"TangentZDelta":{"X":-7.333149e-9,"Y":0.0,"Z":7.677073e-9},"SourceIdx":214},{"PositionDelta":{"X":0.3432865,"Y":0.0,"Z":0.0},"TangentZDelta":{"X":0.0,"Y":0.0,"Z":0.0},"SourceIdx":215},{"PositionDelta":{"X":0.12454319,"Y":0.0,"Z":0.0},"TangentZDelta":{"X":0.0,"Y":0.0,"Z":0.0},"SourceIdx":216},{"PositionDelta":{"X":0.24526215,"Y":0.0,"Z":0.0},"TangentZDelta":{"X":0.0,"Y":0.0,"Z":0.0},"SourceIdx":217},{"PositionDelta":{"X":0.123075485,"Y":0.0,"Z":0.0},"TangentZDelta":{"X":0.0,"Y":0.0,"Z":0.0},"SourceIdx":930}],"NumBaseMeshVerts":50,"SectionIndices":[0],"bGeneratedByEngine":false}]},{"Type":"MorphTarget","Name":"heat_bp","Outer":"SK_Shadowknight_VR2_Dark_Confuse_T05","Class":"UScriptClass'MorphTarget'","Properties":{"BaseSkelMesh":{"ObjectName":"SkeletalMesh'SK_Shadowknight_VR2_Dark_Confuse_T05'","ObjectPath":"WorldExplorers/Content/Characters/Classes/Shadowknight/Dark_Confuse/SK_Shadowknight_VR2_Dark_Confuse_T05.2"}},"MorphLODModels":[{"Vertices":[{"PositionDelta":{"X":-0.09464455,"Y":0.0,"Z":-0.2269516},"TangentZDelta":{"X":1.3847856e-10,"Y":0.0,"Z":6.1795347e-10},"SourceIdx":1439},{"PositionDelta":{"X":0.0106983185,"Y":0.0,"Z":0.08677673},"TangentZDelta":{"X":0.0,"Y":0.0,"Z":0.0},"SourceIdx":1476},{"PositionDelta":{"X":-0.020799637,"Y":0.0,"Z":0.036956787},"TangentZDelta":{"X":-2.3106352e-9,"Y":0.0,"Z":-1.9066718e-8},"SourceIdx":1478},{"PositionDelta":{"X":0.008975983,"Y":0.0,"Z":0.106536865},"TangentZDelta":{"X":1.7140778e-9,"Y":0.0,"Z":1.9603434e-8},"SourceIdx":1479},{"PositionDelta":{"X":0.010124207,"Y":0.0,"Z":0.079338074},"TangentZDelta":{"X":2.1172184e-9,"Y":0.0,"Z":2.1791315e-9},"SourceIdx":1480},{"PositionDelta":{"X":0.0069675446,"Y":0.0,"Z":0.16075897},"TangentZDelta":{"X":-1.370509e-9,"Y":0.0,"Z":5.091328e-8},"SourceIdx":1481},{"PositionDelta":{"X":0.008960724,"Y":0.0,"Z":0.10652161},"TangentZDelta":{"X":-4.575627e-9,"Y":0.0,"Z":2.6786896e-8},"SourceIdx":1482},{"PositionDelta":{"X":0.0016918182,"Y":0.0,"Z":0.023773193},"TangentZDelta":{"X":-2.0318396e-9,"Y":0.0,"Z":-4.9926285e-9},"SourceIdx":1484}],"NumBaseMeshVerts":8,"SectionIndices":[0],"bGeneratedByEngine":false}]},{"Type":"SkeletalMesh","Name":"SK_Shadowknight_VR2_Dark_Confuse_T05","Class":"UScriptClass'SkeletalMesh'","Properties":{"Skeleton":{"ObjectName":"Skeleton'SK_Shadowknight_VR2_Dark_Confuse_T06_Skeleton'","ObjectPath":"WorldExplorers/Content/Characters/Classes/Shadowknight/Dark_Confuse/SK_Shadowknight_VR2_Dark_Confuse_T06_Skeleton.0"},"PositiveBoundsExtension":{"X":50.0,"Y":0.0,"Z":50.0},"NegativeBoundsExtension":{"X":50.0,"Y":0.0,"Z":0.0},"LODInfo":[{"ScreenSize":{"bCooked":true,"Default":1.0,"Value":1.0},"LODHysteresis":0.02,"LODMaterialMap":[],"BuildSettings":{"bRecomputeNormals":true,"bRecomputeTangents":true,"bUseMikkTSpace":true,"bComputeWeightedNormals":false,"bRemoveDegenerates":true,"bUseHighPrecisionTangentBasis":false,"bUseFullPrecisionUVs":false,"bBuildAdjacencyBuffer":true,"ThresholdPosition":0.00002,"ThresholdTangentNormal":0.00002,"ThresholdUV":0.0009765625},"ReductionSettings":{"TerminationCriterion":"SMTC_NumOfTriangles","NumOfTrianglesPercentage":1.0,"NumOfVertPercentage":1.0,"MaxNumOfTriangles":4,"MaxNumOfVerts":6,"MaxDeviationPercentage":0.0,"ReductionMethod":"SMOT_NumOfTriangles","SilhouetteImportance":"SMOI_Normal","TextureImportance":"SMOI_Normal","ShadingImportance":"SMOI_Normal","SkinningImportance":"SMOI_Normal","bRemapMorphTargets":false,"bRecalcNormals":true,"WeldingThreshold":0.1,"NormalsThreshold":60.0,"MaxBonesPerVertex":4,"bEnforceBoneBoundaries":false,"VolumeImportance":1.0,"bLockEdges":false,"BaseLOD":0},"BonesToRemove":[],"BonesToPrioritize":[],"WeightOfPrioritization":1.0,"BakePose":null,"BakePoseOverride":null,"SourceImportFilename":"","bHasBeenSimplified":false,"bHasPerLODVertexColors":false,"bAllowCPUAccess":false,"bSupportUniformlyDistributedSampling":false}],"MorphTargets":[{"ObjectName":"MorphTarget'SK_Shadowknight_VR2_Dark_Confuse_T05:body_bp'","ObjectPath":"WorldExplorers/Content/Characters/Classes/Shadowknight/Dark_Confuse/SK_Shadowknight_VR2_Dark_Confuse_T05.0"},{"ObjectName":"MorphTarget'SK_Shadowknight_VR2_Dark_Confuse_T05:heat_bp'","ObjectPath":"WorldExplorers/Content/Characters/Classes/Shadowknight/Dark_Confuse/SK_Shadowknight_VR2_Dark_Confuse_T05.1"}],"SamplingInfo":{"BuiltData":{"WholeMeshBuiltData":[{"AreaWeightedTriangleSampler":{"Prob":[],"Alias":[],"TotalWeight":0.0}}]}}},"ImportedBounds":{"Origin":{"X":-4.750618,"Y":1.2962817,"Z":84.41839},"BoxExtent":{"X":87.42855,"Y":0.5003228,"Z":85.263824},"SphereRadius":122.12257},"Materials":[null],"LODModels":[{"Sections":[{"MaterialIndex":0,"BaseIndex":0,"NumTriangles":1549,"bRecomputeTangent":false,"RecomputeTangentsVertexMaskChannel":"Alpha","bCastShadow":true,"bVisibleInRayTracing":true,"bLegacyClothingSection":false,"CorrespondClothSectionIndex":-1,"BaseVertexIndex":0,"NumVertices":1549,"MaxBoneInfluences":4,"bUse16BitBoneIndex":false,"CorrespondClothAssetIndex":-1,"bDisabled":false,"GenerateUpToLodIndex":-1,"OriginalDataSectionIndex":-1,"ChunkedParentSectionIndex":-1}],"NumVertices":1549,"NumTexCoords":1,"VertexBufferGPUSkin":{"NumTexCoords":0,"MeshExtension":{"X":0.0,"Y":0.0,"Z":0.0},"MeshOrigin":{"X":0.0,"Y":0.0,"Z":0.0},"bUseFullPrecisionUVs":true,"bExtraBoneInfluences":false}}]}]