[{"Type":"Skeleton","Name":"SK_SpiritWarrior_VR2_Light_KindFist_T05_Skeleton","Class":"UScriptClass'Skeleton'","Properties":{"BoneTree":[{"TranslationRetargetingMode":"EBoneTranslationRetargetingMode::Animation"},{"TranslationRetargetingMode":"EBoneTranslationRetargetingMode::Animation"},{"TranslationRetargetingMode":"EBoneTranslationRetargetingMode::Animation"},{"TranslationRetargetingMode":"EBoneTranslationRetargetingMode::Animation"},{"TranslationRetargetingMode":"EBoneTranslationRetargetingMode::Animation"},{"TranslationRetargetingMode":"EBoneTranslationRetargetingMode::Animation"},{"TranslationRetargetingMode":"EBoneTranslationRetargetingMode::Animation"},{"TranslationRetargetingMode":"EBoneTranslationRetargetingMode::Animation"},{"TranslationRetargetingMode":"EBoneTranslationRetargetingMode::Animation"},{"TranslationRetargetingMode":"EBoneTranslationRetargetingMode::Animation"},{"TranslationRetargetingMode":"EBoneTranslationRetargetingMode::Animation"},{"TranslationRetargetingMode":"EBoneTranslationRetargetingMode::Animation"},{"TranslationRetargetingMode":"EBoneTranslationRetargetingMode::Animation"},{"TranslationRetargetingMode":"EBoneTranslationRetargetingMode::Animation"},{"TranslationRetargetingMode":"EBoneTranslationRetargetingMode::Animation"},{"TranslationRetargetingMode":"EBoneTranslationRetargetingMode::Animation"},{"TranslationRetargetingMode":"EBoneTranslationRetargetingMode::Animation"},{"TranslationRetargetingMode":"EBoneTranslationRetargetingMode::Animation"},{"TranslationRetargetingMode":"EBoneTranslationRetargetingMode::Animation"},{"TranslationRetargetingMode":"EBoneTranslationRetargetingMode::Animation"}]},"ReferenceSkeleton":{"FinalRefBoneInfo":[{"Name":"root","ParentIndex":-1},{"Name":"pelvis","ParentIndex":0},{"Name":"spine","ParentIndex":1},{"Name":"head","ParentIndex":2},{"Name":"arm_l","ParentIndex":2},{"Name":"elbow_l","ParentIndex":4},{"Name":"hand_l","ParentIndex":5},{"Name":"arm_r","ParentIndex":2},{"Name":"elbow_r","ParentIndex":7},{"Name":"hand_r","ParentIndex":8},{"Name":"fix","ParentIndex":2},{"Name":"cloth_03","ParentIndex":2},{"Name":"cloth_01","ParentIndex":1},{"Name":"cloth_02","ParentIndex":12},{"Name":"accessories_01","ParentIndex":1},{"Name":"accessories_02","ParentIndex":1},{"Name":"leg_r","ParentIndex":1},{"Name":"knee_r","ParentIndex":16},{"Name":"foot_r","ParentIndex":17},{"Name":"knee_l","ParentIndex":1}],"FinalRefBonePose":[{"Rotation":{"X":0.0,"Y":0.0,"Z":0.0,"W":1.0,"IsNormalized":true,"Size":1.0,"SizeSquared":1.0},"Translation":{"X":0.0,"Y":0.0,"Z":0.0},"Scale3D":{"X":1.0,"Y":1.0,"Z":1.0},"IsRotationNormalized":true},{"Rotation":{"X":0.0,"Y":-0.0,"Z":0.0,"W":-1.0,"IsNormalized":true,"Size":1.0,"SizeSquared":1.0},"Translation":{"X":0.8680493,"Y":-2.842171e-14,"Z":75.58118},"Scale3D":{"X":1.0,"Y":1.0,"Z":1.0},"IsRotationNormalized":true},{"Rotation":{"X":0.0,"Y":-0.0,"Z":0.0,"W":-1.0,"IsNormalized":true,"Size":1.0,"SizeSquared":1.0},"Translation":{"X":-0.014782276,"Y":-2.8414223e-14,"Z":11.850343},"Scale3D":{"X":1.0,"Y":1.0,"Z":1.0},"IsRotationNormalized":true},{"Rotation":{"X":0.0,"Y":-0.0,"Z":0.0,"W":-1.0,"IsNormalized":true,"Size":1.0,"SizeSquared":1.0},"Translation":{"X":-0.33684507,"Y":2.3841856e-8,"Z":11.788129},"Scale3D":{"X":1.0,"Y":1.0,"Z":1.0},"IsRotationNormalized":true},{"Rotation":{"X":0.0,"Y":-0.0,"Z":0.0,"W":-1.0,"IsNormalized":true,"Size":1.0,"SizeSquared":1.0},"Translation":{"X":8.606006,"Y":-2.8431037e-14,"Z":4.5384593},"Scale3D":{"X":1.0,"Y":1.0,"Z":1.0},"IsRotationNormalized":true},{"Rotation":{"X":0.0,"Y":-0.0,"Z":0.0,"W":-1.0,"IsNormalized":true,"Size":1.0,"SizeSquared":1.0},"Translation":{"X":9.640017,"Y":-1.19208865e-8,"Z":-6.275537},"Scale3D":{"X":1.0,"Y":1.0,"Z":1.0},"IsRotationNormalized":true},{"Rotation":{"X":0.0,"Y":-0.0,"Z":0.0,"W":-1.0,"IsNormalized":true,"Size":1.0,"SizeSquared":1.0},"Translation":{"X":9.398168,"Y":-8.527486e-14,"Z":-6.645752},"Scale3D":{"X":1.0,"Y":1.0,"Z":1.0},"IsRotationNormalized":true},{"Rotation":{"X":0.0,"Y":-0.0,"Z":0.0,"W":-1.0,"IsNormalized":true,"Size":1.0,"SizeSquared":1.0},"Translation":{"X":-7.130293,"Y":2.8419524e-14,"Z":0.90415895},"Scale3D":{"X":1.0,"Y":1.0,"Z":1.0},"IsRotationNormalized":true},{"Rotation":{"X":0.0,"Y":-0.0,"Z":0.0,"W":-1.0,"IsNormalized":true,"Size":1.0,"SizeSquared":1.0},"Translation":{"X":-0.4296582,"Y":-8.523926e-14,"Z":-8.575829},"Scale3D":{"X":1.0,"Y":1.0,"Z":1.0},"IsRotationNormalized":true},{"Rotation":{"X":0.0,"Y":-0.0,"Z":0.0,"W":-1.0,"IsNormalized":true,"Size":1.0,"SizeSquared":1.0},"Translation":{"X":-5.248374,"Y":-1.4210855e-14,"Z":-4.524054},"Scale3D":{"X":1.0,"Y":1.0,"Z":1.0},"IsRotationNormalized":true},{"Rotation":{"X":0.0,"Y":-0.0,"Z":0.0,"W":-1.0,"IsNormalized":true,"Size":1.0,"SizeSquared":1.0},"Translation":{"X":0.3267373,"Y":-5.684819e-14,"Z":9.053981},"Scale3D":{"X":1.0,"Y":1.0,"Z":1.0},"IsRotationNormalized":true},{"Rotation":{"X":0.0,"Y":-0.0,"Z":0.0,"W":-1.0,"IsNormalized":true,"Size":1.0,"SizeSquared":1.0},"Translation":{"X":-11.465197,"Y":2.8419524e-14,"Z":1.0697131},"Scale3D":{"X":1.0,"Y":1.0,"Z":1.0},"IsRotationNormalized":true},{"Rotation":{"X":0.0,"Y":-0.0,"Z":0.0,"W":-1.0,"IsNormalized":true,"Size":1.0,"SizeSquared":1.0},"Translation":{"X":-12.604298,"Y":5.3006983e-18,"Z":-6.5017424},"Scale3D":{"X":1.0,"Y":1.0,"Z":1.0},"IsRotationNormalized":true},{"Rotation":{"X":0.0,"Y":-0.0,"Z":0.0,"W":-1.0,"IsNormalized":true,"Size":1.0,"SizeSquared":1.0},"Translation":{"X":-6.655816,"Y":-0.0,"Z":-1.6957114},"Scale3D":{"X":1.0,"Y":1.0,"Z":1.0},"IsRotationNormalized":true},{"Rotation":{"X":0.0,"Y":-0.0,"Z":0.0,"W":-1.0,"IsNormalized":true,"Size":1.0,"SizeSquared":1.0},"Translation":{"X":7.577074,"Y":1.4242022e-14,"Z":-4.5537605},"Scale3D":{"X":1.0,"Y":1.0,"Z":1.0},"IsRotationNormalized":true},{"Rotation":{"X":0.0,"Y":-0.0,"Z":0.0,"W":-1.0,"IsNormalized":true,"Size":1.0,"SizeSquared":1.0},"Translation":{"X":-10.088091,"Y":1.4242022e-14,"Z":-15.231957},"Scale3D":{"X":1.0,"Y":1.0,"Z":1.0},"IsRotationNormalized":true},{"Rotation":{"X":0.0,"Y":-0.0,"Z":0.0,"W":-1.0,"IsNormalized":true,"Size":1.0,"SizeSquared":1.0},"Translation":{"X":-5.0054197,"Y":1.4242022e-14,"Z":-15.18142},"Scale3D":{"X":1.0,"Y":1.0,"Z":1.0},"IsRotationNormalized":true},{"Rotation":{"X":0.0,"Y":-0.0,"Z":0.0,"W":-1.0,"IsNormalized":true,"Size":1.0,"SizeSquared":1.0},"Translation":{"X":0.5011591,"Y":5.9604925e-9,"Z":-15.832139},"Scale3D":{"X":1.0,"Y":1.0,"Z":1.0},"IsRotationNormalized":true},{"Rotation":{"X":0.0,"Y":-0.0,"Z":0.0,"W":-1.0,"IsNormalized":true,"Size":1.0,"SizeSquared":1.0},"Translation":{"X":5.409644,"Y":1.5782906e-15,"Z":-16.522171},"Scale3D":{"X":1.0,"Y":1.0,"Z":1.0},"IsRotationNormalized":true},{"Rotation":{"X":0.0,"Y":-0.0,"Z":0.0,"W":-1.0,"IsNormalized":true,"Size":1.0,"SizeSquared":1.0},"Translation":{"X":15.379419,"Y":1.4242022e-14,"Z":-15.489405},"Scale3D":{"X":1.0,"Y":1.0,"Z":1.0},"IsRotationNormalized":true}],"FinalNameToIndexMap":{"root":0,"pelvis":1,"spine":2,"head":3,"arm_l":4,"elbow_l":5,"hand_l":6,"arm_r":7,"elbow_r":8,"hand_r":9,"fix":10,"cloth_03":11,"cloth_01":12,"cloth_02":13,"accessories_01":14,"accessories_02":15,"leg_r":16,"knee_r":17,"foot_r":18,"knee_l":19}},"Guid":"578AD588-4A241E34-E10296B6-59F8F494","AnimRetargetSources":{},"NameMappings":{"AnimationCurves":{"GuidMap":null,"UidMap":null,"CurveMetaDataMap":{}}},"ExistingMarkerNames":null}]