[{"Type":"BodySetup","Name":"BodySetup_2106","Outer":"SM_BillboardDivider","Class":"UScriptClass'BodySetup'","Properties":{"DefaultInstance":{"ObjectType":"ECC_WorldStatic","CollisionProfileName":"BlockAll"}},"BodySetupGuid":"8EFB921A4B9AC00AC0B20384879A3B23","CookedFormatData":{"PhysXPC":{"BulkDataFlags":"BULKDATA_SingleUse | BULKDATA_ForceInlinePayload","ElementCount":25233,"SizeOnDisk":25233,"OffsetInFile":"0xD3B6"}}},{"Type":"NavCollision","Name":"NavCollision_75","Outer":"SM_BillboardDivider","Class":"UScriptClass'NavCollision'","CookedFormatData":{"NavCollision_X":{"BulkDataFlags":"BULKDATA_SingleUse | BULKDATA_ForceInlinePayload","ElementCount":21,"SizeOnDisk":21,"OffsetInFile":"0x1368F"}}},{"Type":"StaticMesh","Name":"SM_BillboardDivider","Class":"UScriptClass'StaticMesh'","Properties":{"StaticMaterials":[{"MaterialInterface":{"ObjectName":"Material'WorldGridMaterial'","ObjectPath":"Engine/Content/EngineMaterials/WorldGridMaterial.0"},"MaterialSlotName":"WorldGridMaterial","ImportedMaterialSlotName":"WorldGridMaterial","UVChannelData":{"bInitialized":true,"bOverrideDensities":false,"LocalUVDensities":0.0}}],"LightmapUVDensity":0.96905524,"LightMapResolution":32,"LightMapCoordinateIndex":1,"ExtendedBounds":{"Origin":{"X":0.0,"Y":-123.289246,"Z":32.9646},"BoxExtent":{"X":473.41495,"Y":161.7854,"Z":32.464607},"SphereRadius":498.55334}},"BodySetup":{"ObjectName":"BodySetup'SM_BillboardDivider:BodySetup_2106'","ObjectPath":"WorldExplorers/Content/World/Backgrounds/BaseMesh/SM_BillboardDivider.0"},"NavCollision":{"ObjectName":"NavCollision'SM_BillboardDivider:NavCollision_75'","ObjectPath":"WorldExplorers/Content/World/Backgrounds/BaseMesh/SM_BillboardDivider.1"},"LightingGuid":"29407718-46522B54-4D3F06A0-3DE6BF4F","RenderData":{"LODs":[{"Sections":[{"MaterialIndex":0,"FirstIndex":0,"NumTriangles":320,"MinVertexIndex":0,"MaxVertexIndex":241,"bEnableCollision":true,"bCastShadow":true,"bForceOpaque":false,"bVisibleInRayTracing":true}],"MaxDeviation":0.0,"PositionVertexBuffer":{"Stride":12,"NumVertices":242},"VertexBuffer":{"NumTexCoords":2,"NumVertices":242,"Strides":-1,"UseHighPrecisionTangentBasis":false,"UseFullPrecisionUVs":false},"ColorVertexBuffer":{"Stride":4,"NumVertices":242}}],"Bounds":{"Origin":{"X":0.0,"Y":-123.289246,"Z":32.9646},"BoxExtent":{"X":473.41495,"Y":161.7854,"Z":32.464607},"SphereRadius":498.55334},"bLODsShareStaticLighting":true,"ScreenSize":[1.0,0.0,0.0,0.0,0.0,0.0,0.0,0.0]}}]