[{"Type":"Texture2D","Name":"T_Blademaster_SR2_Light_DualAssault_T05_Icon","Class":"UScriptClass'Texture2D'","Properties":{"ImportedSize":{"X":256,"Y":256},"LightingGuid":"ED85C10F-40DCC820-D0DE08BA-E0A7FC86","LODGroup":"TEXTUREGROUP_UI"},"SizeX":256,"SizeY":256,"PackedData":1,"PixelFormat":"PF_DXT1","FirstMipToSerialize":0,"Mips":[{"BulkData":{"BulkDataFlags":"BULKDATA_SingleUse | BULKDATA_ForceInlinePayload","ElementCount":32768,"SizeOnDisk":32768,"OffsetInFile":"0x890C"},"SizeX":256,"SizeY":256,"SizeZ":1}]}]