[{"Type":"DistributionFloatConstant","Name":"RequiredDistributionSpawnRate","Outer":"ParticleModuleRequired_1","Class":"UScriptClass'DistributionFloatConstant'"},{"Type":"ParticleLODLevel","Name":"ParticleLODLevel_1","Outer":"ParticleSpriteEmitter_1","Class":"UScriptClass'ParticleLODLevel'","Properties":{"RequiredModule":{"ObjectName":"ParticleModuleRequired'P_Smoke:ParticleModuleRequired_1'","ObjectPath":"WorldExplorers/Content/Effects/Map/P_Smoke.8"},"Modules":[{"ObjectName":"ParticleModuleLocation'P_Smoke:ParticleModuleLocation_3'","ObjectPath":"WorldExplorers/Content/Effects/Map/P_Smoke.6"},{"ObjectName":"ParticleModuleLifetime'P_Smoke:ParticleModuleLifetime_1'","ObjectPath":"WorldExplorers/Content/Effects/Map/P_Smoke.5"},{"ObjectName":"ParticleModuleSize'P_Smoke:ParticleModuleSize_1'","ObjectPath":"WorldExplorers/Content/Effects/Map/P_Smoke.11"},{"ObjectName":"ParticleModuleVelocity'P_Smoke:ParticleModuleVelocity_12'","ObjectPath":"WorldExplorers/Content/Effects/Map/P_Smoke.14"},{"ObjectName":"ParticleModuleSizeMultiplyLife'P_Smoke:ParticleModuleSizeMultiplyLife_0'","ObjectPath":"WorldExplorers/Content/Effects/Map/P_Smoke.12"},{"ObjectName":"ParticleModuleRotation'P_Smoke:ParticleModuleRotation_0'","ObjectPath":"WorldExplorers/Content/Effects/Map/P_Smoke.9"},{"ObjectName":"ParticleModuleRotationRate'P_Smoke:ParticleModuleRotationRate_0'","ObjectPath":"WorldExplorers/Content/Effects/Map/P_Smoke.10"},{"ObjectName":"ParticleModuleAccelerationDrag'P_Smoke:ParticleModuleAccelerationDrag_0'","ObjectPath":"WorldExplorers/Content/Effects/Map/P_Smoke.2"},{"ObjectName":"ParticleModuleAccelerationOverLifetime'P_Smoke:ParticleModuleAccelerationOverLifetime_0'","ObjectPath":"WorldExplorers/Content/Effects/Map/P_Smoke.3"},{"ObjectName":"ParticleModuleParameterDynamic'P_Smoke:ParticleModuleParameterDynamic_0'","ObjectPath":"WorldExplorers/Content/Effects/Map/P_Smoke.7"},{"ObjectName":"ParticleModuleColorOverLife'P_Smoke:ParticleModuleColorOverLife_3'","ObjectPath":"WorldExplorers/Content/Effects/Map/P_Smoke.4"}],"SpawnModule":{"ObjectName":"ParticleModuleSpawn'P_Smoke:ParticleModuleSpawn_2'","ObjectPath":"WorldExplorers/Content/Effects/Map/P_Smoke.13"},"PeakActiveParticles":7}},{"Type":"ParticleModuleAccelerationDrag","Name":"ParticleModuleAccelerationDrag_0","Outer":"P_Smoke","Class":"UScriptClass'ParticleModuleAccelerationDrag'","Properties":{"DragCoefficientRaw":{"MinValue":0.13,"MaxValue":0.13,"Distribution":null,"Table":{"Values":[0.13],"Op":1,"EntryCount":1,"EntryStride":1}},"bAlwaysInWorldSpace":true,"LODValidity":1}},{"Type":"ParticleModuleAccelerationOverLifetime","Name":"ParticleModuleAccelerationOverLifetime_0","Outer":"P_Smoke","Class":"UScriptClass'ParticleModuleAccelerationOverLifetime'","Properties":{"AccelOverLife":{"MaxValue":4.0,"MaxValueVec":{"X":0.0,"Y":1.0,"Z":0.0},"Distribution":null,"Table":{"TimeScale":1.0,"Values":[0.0,0.0,0.0,0.0,0.0,0.0,0.0,4.0,0.0,0.0,1.0,0.0],"Op":2,"EntryCount":2,"EntryStride":6,"SubEntryStride":3}},"bAlwaysInWorldSpace":true,"LODValidity":1}},{"Type":"ParticleModuleColorOverLife","Name":"ParticleModuleColorOverLife_3","Outer":"P_Smoke","Class":"UScriptClass'ParticleModuleColorOverLife'","Properties":{"ColorOverLife":{"MinValue":0.0040811873,"MaxValue":0.45250937,"MinValueVec":{"X":0.011756397,"Y":0.00769123,"Z":0.0040811873},"MaxValueVec":{"X":0.45250937,"Y":0.2587986,"Z":0.18615945},"Distribution":null,"Table":{"TimeScale":1.9144256,"TimeBias":0.024912212,"Values":[0.45250937,0.2587986,0.18615945,0.011756424,0.0076912455,0.004081198],"Op":1,"EntryCount":2,"EntryStride":3}},"AlphaOverLife":{"MaxValue":1.0,"Distribution":null,"Table":{"TimeScale":31.0,"Values":[0.0,0.32041785,0.6408357,0.95631826,0.99595875,0.99136156,0.9867644,0.9821671,0.97756994,0.97297275,0.96837556,0.9637784,0.9591812,0.954584,0.9499869,0.9453896,0.9400646,0.89770204,0.80273193,0.67124826,0.5193533,0.3631699,0.21894325,0.10279095,0.030814452,0.0140488185,0.011707344,0.0093658725,0.0070244116,0.0046829456,0.0023414704,0.0],"Op":1,"EntryCount":32,"EntryStride":1}},"LODValidity":1}},{"Type":"ParticleModuleLifetime","Name":"ParticleModuleLifetime_1","Outer":"P_Smoke","Class":"UScriptClass'ParticleModuleLifetime'","Properties":{"Lifetime":{"MinValue":6.0,"MaxValue":12.0,"Distribution":null,"Table":{"Values":[6.0,12.0],"Op":2,"EntryCount":1,"EntryStride":2,"SubEntryStride":1}},"LODValidity":1}},{"Type":"ParticleModuleLocation","Name":"ParticleModuleLocation_3","Outer":"P_Smoke","Class":"UScriptClass'ParticleModuleLocation'","Properties":{"StartLocation":{"MinValue":-2.0,"MaxValue":1.0,"MinValueVec":{"X":0.0,"Y":-2.0,"Z":-1.0},"MaxValueVec":{"X":-2.0,"Y":1.0,"Z":1.0},"Distribution":null,"Table":{"Values":[0.0,-2.0,-1.0,-2.0,1.0,1.0],"Op":2,"EntryCount":1,"EntryStride":6,"SubEntryStride":3}},"LODValidity":1}},{"Type":"ParticleModuleParameterDynamic","Name":"ParticleModuleParameterDynamic_0","Outer":"P_Smoke","Class":"UScriptClass'ParticleModuleParameterDynamic'","Properties":{"DynamicParams":[{"ParamName":"None","bUseEmitterTime":false,"bSpawnTimeOnly":false,"ValueMethod":"EDPV_UserSet","bScaleVelocityByParamValue":false,"ParamValue":{"MinValue":1.0,"MaxValue":1.0,"Distribution":null,"Table":{"TimeScale":0.0,"TimeBias":0.0,"Values":[1.0],"Op":1,"EntryCount":1,"EntryStride":1,"SubEntryStride":0,"LockFlag":0}}},{"ParamName":"None","bUseEmitterTime":false,"bSpawnTimeOnly":false,"ValueMethod":"EDPV_UserSet","bScaleVelocityByParamValue":false,"ParamValue":{"MinValue":0.1,"MaxValue":1.0,"Distribution":null,"Table":{"TimeScale":6.666667,"TimeBias":0.0,"Values":[0.1,0.2511811,0.625,1.0],"Op":1,"EntryCount":4,"EntryStride":1,"SubEntryStride":0,"LockFlag":0}}},{"ParamName":"None","bUseEmitterTime":false,"bSpawnTimeOnly":false,"ValueMethod":"EDPV_UserSet","bScaleVelocityByParamValue":false,"ParamValue":{"MinValue":1.0,"MaxValue":1.0,"Distribution":null,"Table":{"TimeScale":0.0,"TimeBias":0.0,"Values":[1.0],"Op":1,"EntryCount":1,"EntryStride":1,"SubEntryStride":0,"LockFlag":0}}},{"ParamName":"None","bUseEmitterTime":false,"bSpawnTimeOnly":false,"ValueMethod":"EDPV_UserSet","bScaleVelocityByParamValue":false,"ParamValue":{"MinValue":1.0,"MaxValue":1.0,"Distribution":null,"Table":{"TimeScale":0.0,"TimeBias":0.0,"Values":[1.0],"Op":1,"EntryCount":1,"EntryStride":1,"SubEntryStride":0,"LockFlag":0}}}],"UpdateFlags":15,"LODValidity":1}},{"Type":"ParticleModuleRequired","Name":"ParticleModuleRequired_1","Outer":"P_Smoke","Class":"UScriptClass'ParticleModuleRequired'","Properties":{"Material":{"ObjectName":"Material'M_VolcanoSmoke_Dynamic'","ObjectPath":"WorldExplorers/Content/Effects/Textures/M_VolcanoSmoke_Dynamic.0"},"EmitterOrigin":{"X":0.0,"Y":-1.0,"Z":0.0},"bUseLocalSpace":true,"SortMode":"PSORTMODE_Age_NewestFirst","bUseLegacyEmitterTime":false,"EmitterDuration":2.0,"SpawnRate":{"Distribution":{"ObjectName":"DistributionFloatConstant'P_Smoke:ParticleModuleRequired_1.RequiredDistributionSpawnRate'","ObjectPath":"WorldExplorers/Content/Effects/Map/P_Smoke.0"}},"RandomImageTime":1.0,"LODValidity":1}},{"Type":"ParticleModuleRotation","Name":"ParticleModuleRotation_0","Outer":"P_Smoke","Class":"UScriptClass'ParticleModuleRotation'","Properties":{"StartRotation":{"MinValue":-1.0,"MaxValue":1.0,"Distribution":null,"Table":{"Values":[-1.0,1.0],"Op":2,"EntryCount":1,"EntryStride":2,"SubEntryStride":1}},"LODValidity":1}},{"Type":"ParticleModuleRotationRate","Name":"ParticleModuleRotationRate_0","Outer":"P_Smoke","Class":"UScriptClass'ParticleModuleRotationRate'","Properties":{"StartRotationRate":{"MinValue":-0.2,"MaxValue":0.2,"Distribution":null,"Table":{"Values":[-0.2,0.2],"Op":2,"EntryCount":1,"EntryStride":2,"SubEntryStride":1}},"LODValidity":1}},{"Type":"ParticleModuleSize","Name":"ParticleModuleSize_1","Outer":"P_Smoke","Class":"UScriptClass'ParticleModuleSize'","Properties":{"StartSize":{"MinValue":25.0,"MaxValue":40.0,"MinValueVec":{"X":25.0,"Y":25.0,"Z":25.0},"MaxValueVec":{"X":40.0,"Y":26.0,"Z":26.0},"Distribution":null,"Table":{"Values":[25.0,25.0,25.0,40.0,26.0,26.0],"Op":2,"EntryCount":1,"EntryStride":6,"SubEntryStride":3}},"LODValidity":1}},{"Type":"ParticleModuleSizeMultiplyLife","Name":"ParticleModuleSizeMultiplyLife_0","Outer":"P_Smoke","Class":"UScriptClass'ParticleModuleSizeMultiplyLife'","Properties":{"LifeMultiplier":{"MinValue":0.4,"MaxValue":2.5903363,"MinValueVec":{"X":0.4,"Y":0.66901684,"Z":0.6697765},"MaxValueVec":{"X":2.5903363,"Y":2.5561576,"Z":2.4877977},"Distribution":null,"Table":{"TimeScale":7.058797,"Values":[0.4,0.7,0.7,0.6859413,0.68976676,0.6900177,1.0670017,1.0380008,1.0297139,1.4569395,1.3971251,1.3800336,1.8468772,1.7562495,1.730353,2.2246296,2.1074438,2.072284,2.4074829,2.331801,2.280041,2.5903363,2.5561576,2.4877977],"Op":1,"EntryCount":8,"EntryStride":3}},"LODValidity":1}},{"Type":"ParticleModuleSpawn","Name":"ParticleModuleSpawn_2","Outer":"P_Smoke","Class":"UScriptClass'ParticleModuleSpawn'","Properties":{"Rate":{"Distribution":null,"Table":{"Values":[0.0],"Op":1,"EntryCount":1,"EntryStride":1}},"RateScale":{"MinValue":1.0,"MaxValue":1.0,"Distribution":null,"Table":{"Values":[1.0],"Op":1,"EntryCount":1,"EntryStride":1}},"BurstList":[{"Count":1,"CountLow":-1,"Time":0.0}],"BurstScale":{"MinValue":1.0,"MaxValue":1.0,"Distribution":null,"Table":{"Values":[1.0],"Op":1,"EntryCount":1,"EntryStride":1}},"bApplyGlobalSpawnRateScale":false,"LODValidity":1}},{"Type":"ParticleModuleVelocity","Name":"ParticleModuleVelocity_12","Outer":"P_Smoke","Class":"UScriptClass'ParticleModuleVelocity'","Properties":{"StartVelocity":{"MinValue":-5.0,"MaxValue":10.0,"MinValueVec":{"X":-5.0,"Y":4.0,"Z":7.0},"MaxValueVec":{"X":-2.0,"Y":8.0,"Z":10.0},"Distribution":null,"Table":{"Values":[-5.0,4.0,7.0,-2.0,8.0,10.0],"Op":2,"EntryCount":1,"EntryStride":6,"SubEntryStride":3}},"StartVelocityRadial":{"Distribution":null,"Table":{"Values":[0.0],"Op":1,"EntryCount":1,"EntryStride":1}},"LODValidity":1}},{"Type":"ParticleSpriteEmitter","Name":"ParticleSpriteEmitter_1","Outer":"P_Smoke","Class":"UScriptClass'ParticleSpriteEmitter'","Properties":{"EmitterName":"Main Smoke","bUseLegacySpawningBehavior":true,"LODLevels":[{"ObjectName":"ParticleLODLevel'P_Smoke:ParticleSpriteEmitter_1.ParticleLODLevel_1'","ObjectPath":"WorldExplorers/Content/Effects/Map/P_Smoke.1"}],"DetailModeBitmask":7}},{"Type":"ParticleSystem","Name":"P_Smoke","Class":"UScriptClass'ParticleSystem'","Properties":{"WarmupTime":25.0,"Emitters":[{"ObjectName":"ParticleSpriteEmitter'P_Smoke:ParticleSpriteEmitter_1'","ObjectPath":"WorldExplorers/Content/Effects/Map/P_Smoke.15"}],"CurveEdSetup":null,"LODDistances":[0.0],"LODSettings":[{}],"FixedRelativeBoundingBox":{"Min":{"X":-8000.0,"Y":-8000.0,"Z":-8000.0},"Max":{"X":8000.0,"Y":8000.0,"Z":8000.0},"IsValid":1},"bUseFixedRelativeBoundingBox":true,"bShouldResetPeakCounts":true,"LODMethod":"PARTICLESYSTEMLODMETHOD_DirectSet","CustomOcclusionBounds":{"Min":{"X":0.0,"Y":0.0,"Z":0.0},"Max":{"X":0.0,"Y":0.0,"Z":0.0},"IsValid":1}}}]