[{"Type":"SoundCue","Name":"Mage_F_Healed_Cue","Class":"UScriptClass'SoundCue'","Properties":{"FirstNode":{"ObjectName":"SoundNodeDelay'Mage_F_Healed_Cue:SoundNodeDelay_21'","ObjectPath":"WorldExplorers/Content/Audio/Heroes/Mage_Female/Mage_F_Healed_Cue.1"},"VolumeMultiplier":0.8,"SoundClassObject":{"ObjectName":"SoundClass'Normal_Hero_Combat_Sounds'","ObjectPath":"WorldExplorers/Content/Audio/SoundClasses/Normal_Hero_Combat_Sounds.0"},"bHasDelayNode":true,"ConcurrencySet":[{"ObjectName":"SoundConcurrency'CNC_Mage_F_Voice'","ObjectPath":"WorldExplorers/Content/Audio/Heroes/Mage_Female/CNC_Mage_F_Voice.0"}],"ConcurrencyOverrides":{"MaxCount":1,"ResolutionRule":"EMaxConcurrentResolutionRule::StopOldest"},"Duration":2.6460319,"MaxDistance":2097152.0}},{"Type":"SoundNodeDelay","Name":"SoundNodeDelay_21","Outer":"Mage_F_Healed_Cue","Class":"UScriptClass'SoundNodeDelay'","Properties":{"DelayMax":1.0,"ChildNodes":[{"ObjectName":"SoundNodeModulator'Mage_F_Healed_Cue:SoundNodeModulator_13'","ObjectPath":"WorldExplorers/Content/Audio/Heroes/Mage_Female/Mage_F_Healed_Cue.2"}]}},{"Type":"SoundNodeModulator","Name":"SoundNodeModulator_13","Outer":"Mage_F_Healed_Cue","Class":"UScriptClass'SoundNodeModulator'","Properties":{"ChildNodes":[{"ObjectName":"SoundNodeRandom'Mage_F_Healed_Cue:SoundNodeRandom_240'","ObjectPath":"WorldExplorers/Content/Audio/Heroes/Mage_Female/Mage_F_Healed_Cue.3"}]}},{"Type":"SoundNodeRandom","Name":"SoundNodeRandom_240","Outer":"Mage_F_Healed_Cue","Class":"UScriptClass'SoundNodeRandom'","Properties":{"Weights":[1.0,1.0],"ChildNodes":[{"ObjectName":"SoundNodeWavePlayer'Mage_F_Healed_Cue:SoundNodeWavePlayer_737'","ObjectPath":"WorldExplorers/Content/Audio/Heroes/Mage_Female/Mage_F_Healed_Cue.4"},{"ObjectName":"SoundNodeWavePlayer'Mage_F_Healed_Cue:SoundNodeWavePlayer_738'","ObjectPath":"WorldExplorers/Content/Audio/Heroes/Mage_Female/Mage_F_Healed_Cue.5"}]}},{"Type":"SoundNodeWavePlayer","Name":"SoundNodeWavePlayer_737","Outer":"Mage_F_Healed_Cue","Class":"UScriptClass'SoundNodeWavePlayer'","Properties":{"SoundWaveAssetPtr":{"AssetPathName":"/Game/Audio/Heroes/Mage_Female/mage_f_Healed_01.mage_f_Healed_01","SubPathString":""}},"SoundWave":null},{"Type":"SoundNodeWavePlayer","Name":"SoundNodeWavePlayer_738","Outer":"Mage_F_Healed_Cue","Class":"UScriptClass'SoundNodeWavePlayer'","Properties":{"SoundWaveAssetPtr":{"AssetPathName":"/Game/Audio/Heroes/Mage_Female/mage_f_Healed_02.mage_f_Healed_02","SubPathString":""}},"SoundWave":null}]