[{"Type":"BodySetup","Name":"BodySetup_0","Outer":"S_StartScreen_Front_Rock","Class":"UScriptClass'BodySetup'","Properties":{"DefaultInstance":{"ObjectType":"ECC_WorldStatic","CollisionProfileName":"BlockAll"}},"BodySetupGuid":"B92531AD4054EEA048D02EB5F48CCD85","CookedFormatData":{"PhysXPC":{"BulkDataFlags":"BULKDATA_SingleUse | BULKDATA_ForceInlinePayload","ElementCount":2109,"SizeOnDisk":2109,"OffsetInFile":"0x2614"}}},{"Type":"NavCollision","Name":"NavCollision_0","Outer":"S_StartScreen_Front_Rock","Class":"UScriptClass'NavCollision'","CookedFormatData":{"NavCollision_X":{"BulkDataFlags":"BULKDATA_SingleUse | BULKDATA_ForceInlinePayload","ElementCount":21,"SizeOnDisk":21,"OffsetInFile":"0x2E99"}}},{"Type":"StaticMesh","Name":"S_StartScreen_Front_Rock","Class":"UScriptClass'StaticMesh'","Properties":{"StaticMaterials":[{"MaterialInterface":{"ObjectName":"Material'M_Particle_Parts'","ObjectPath":"WorldExplorers/Content/Menus/StartScreen/Full/M_Particle_Parts.0"},"MaterialSlotName":"M_Particle_Parts","ImportedMaterialSlotName":"M_Particle_Parts","UVChannelData":{"bInitialized":true,"bOverrideDensities":false,"LocalUVDensities":0.0}}],"LightmapUVDensity":73.67975,"LightMapResolution":64,"LightMapCoordinateIndex":1,"ExtendedBounds":{"Origin":{"X":-1.4498629e-15,"Y":0.0,"Z":0.0},"BoxExtent":{"X":3.1205012e-14,"Y":29.597574,"Z":44.39636},"SphereRadius":50.315876}},"BodySetup":{"ObjectName":"BodySetup'S_StartScreen_Front_Rock:BodySetup_0'","ObjectPath":"WorldExplorers/Content/Menus/StartScreen/Full/S_StartScreen_Front_Rock.0"},"NavCollision":{"ObjectName":"NavCollision'S_StartScreen_Front_Rock:NavCollision_0'","ObjectPath":"WorldExplorers/Content/Menus/StartScreen/Full/S_StartScreen_Front_Rock.1"},"LightingGuid":"D8A4C8E8-46A757C5-8E00BC8E-3A18D6DE","RenderData":{"LODs":[{"Sections":[{"MaterialIndex":0,"FirstIndex":0,"NumTriangles":24,"MinVertexIndex":0,"MaxVertexIndex":21,"bEnableCollision":true,"bCastShadow":true,"bForceOpaque":false,"bVisibleInRayTracing":true}],"MaxDeviation":0.0,"PositionVertexBuffer":{"Stride":12,"NumVertices":22},"VertexBuffer":{"NumTexCoords":2,"NumVertices":22,"Strides":-1,"UseHighPrecisionTangentBasis":false,"UseFullPrecisionUVs":false},"ColorVertexBuffer":{"Stride":0,"NumVertices":0}}],"Bounds":{"Origin":{"X":-1.4498629e-15,"Y":0.0,"Z":0.0},"BoxExtent":{"X":3.1205012e-14,"Y":29.597574,"Z":44.39636},"SphereRadius":50.315876},"bLODsShareStaticLighting":true,"ScreenSize":[1.0,0.0,0.0,0.0,0.0,0.0,0.0,0.0]}}]