[{"Type":"SoundCue","Name":"Robot_M_Special_Defense_cue","Class":"UScriptClass'SoundCue'","Properties":{"FirstNode":{"ObjectName":"SoundNodeModulator'Robot_M_Special_Defense_cue:SoundNodeModulator_6'","ObjectPath":"WorldExplorers/Content/Audio/Heroes/Robot_Male/Robot_M_Special_Defense_cue.1"},"VolumeMultiplier":2.65,"SoundClassObject":{"ObjectName":"SoundClass'Critical_Combat_Sounds_PSM'","ObjectPath":"WorldExplorers/Content/Audio/SoundClasses/Critical_Combat_Sounds_PSM.0"},"ConcurrencySet":[{"ObjectName":"SoundConcurrency'CNC_Robot_M_Special_Voice'","ObjectPath":"WorldExplorers/Content/Audio/Heroes/Robot_Male/CNC_Robot_M_Special_Voice.0"}],"ConcurrencyOverrides":{"ResolutionRule":"EMaxConcurrentResolutionRule::PreventNew"},"Duration":2.203991,"MaxDistance":2097152.0}},{"Type":"SoundNodeModulator","Name":"SoundNodeModulator_6","Outer":"Robot_M_Special_Defense_cue","Class":"UScriptClass'SoundNodeModulator'","Properties":{"ChildNodes":[{"ObjectName":"SoundNodeRandom'Robot_M_Special_Defense_cue:SoundNodeRandom_1'","ObjectPath":"WorldExplorers/Content/Audio/Heroes/Robot_Male/Robot_M_Special_Defense_cue.2"}]}},{"Type":"SoundNodeRandom","Name":"SoundNodeRandom_1","Outer":"Robot_M_Special_Defense_cue","Class":"UScriptClass'SoundNodeRandom'","Properties":{"Weights":[1.0,1.0,1.0,1.0],"ChildNodes":[{"ObjectName":"SoundNodeWavePlayer'Robot_M_Special_Defense_cue:SoundNodeWavePlayer_3'","ObjectPath":"WorldExplorers/Content/Audio/Heroes/Robot_Male/Robot_M_Special_Defense_cue.3"},{"ObjectName":"SoundNodeWavePlayer'Robot_M_Special_Defense_cue:SoundNodeWavePlayer_4'","ObjectPath":"WorldExplorers/Content/Audio/Heroes/Robot_Male/Robot_M_Special_Defense_cue.4"},{"ObjectName":"SoundNodeWavePlayer'Robot_M_Special_Defense_cue:SoundNodeWavePlayer_5'","ObjectPath":"WorldExplorers/Content/Audio/Heroes/Robot_Male/Robot_M_Special_Defense_cue.5"},{"ObjectName":"SoundNodeWavePlayer'Robot_M_Special_Defense_cue:SoundNodeWavePlayer_6'","ObjectPath":"WorldExplorers/Content/Audio/Heroes/Robot_Male/Robot_M_Special_Defense_cue.6"}]}},{"Type":"SoundNodeWavePlayer","Name":"SoundNodeWavePlayer_3","Outer":"Robot_M_Special_Defense_cue","Class":"UScriptClass'SoundNodeWavePlayer'","Properties":{"SoundWaveAssetPtr":{"AssetPathName":"/Game/Audio/Heroes/Robot_Male/Robot_Parry_01.Robot_Parry_01","SubPathString":""}},"SoundWave":null},{"Type":"SoundNodeWavePlayer","Name":"SoundNodeWavePlayer_4","Outer":"Robot_M_Special_Defense_cue","Class":"UScriptClass'SoundNodeWavePlayer'","Properties":{"SoundWaveAssetPtr":{"AssetPathName":"/Game/Audio/Heroes/Robot_Male/Robot_Parry_02.Robot_Parry_02","SubPathString":""}},"SoundWave":null},{"Type":"SoundNodeWavePlayer","Name":"SoundNodeWavePlayer_5","Outer":"Robot_M_Special_Defense_cue","Class":"UScriptClass'SoundNodeWavePlayer'","Properties":{"SoundWaveAssetPtr":{"AssetPathName":"/Game/Audio/Heroes/Robot_Male/Robot_Parry_03.Robot_Parry_03","SubPathString":""}},"SoundWave":null},{"Type":"SoundNodeWavePlayer","Name":"SoundNodeWavePlayer_6","Outer":"Robot_M_Special_Defense_cue","Class":"UScriptClass'SoundNodeWavePlayer'","Properties":{"SoundWaveAssetPtr":{"AssetPathName":"/Game/Audio/Heroes/Robot_Male/Robot_Parry_04.Robot_Parry_04","SubPathString":""}},"SoundWave":null}]