[{"Type":"BodySetup","Name":"BodySetup_0","Outer":"TileCoverRock_FZ","Class":"UScriptClass'BodySetup'","Properties":{"DefaultInstance":{"ObjectType":"ECC_WorldStatic","CollisionEnabled":"ECollisionEnabled::NoCollision","CollisionProfileName":"NoCollision","CollisionResponses":{"ResponseArray":[{"Channel":"Visibility","Response":"ECR_Ignore"},{"Channel":"Camera","Response":"ECR_Ignore"}]}}},"BodySetupGuid":"AE1EFB4A420A2513F6D7CA80C5E4DC8F"},{"Type":"NavCollision","Name":"NavCollision_0","Outer":"TileCoverRock_FZ","Class":"UScriptClass'NavCollision'","CookedFormatData":{"NavCollision_X":{"BulkDataFlags":"BULKDATA_SingleUse | BULKDATA_ForceInlinePayload","ElementCount":21,"SizeOnDisk":21,"OffsetInFile":"0x5C98"}}},{"Type":"StaticMesh","Name":"TileCoverRock_FZ","Class":"UScriptClass'StaticMesh'","Properties":{"StaticMaterials":[{"MaterialInterface":{"ObjectName":"Material'M_TileCover'","ObjectPath":"WorldExplorers/Content/World/Backgrounds/BaseMaterial/M_TileCover.0"},"MaterialSlotName":"M_TileCover","ImportedMaterialSlotName":"M_TileCover","UVChannelData":{"bInitialized":true,"bOverrideDensities":false,"LocalUVDensities":0.0}}],"ExtendedBounds":{"Origin":{"X":-0.000030517578,"Y":0.0,"Z":-25.0},"BoxExtent":{"X":54.999985,"Y":57.27304,"Z":25.0},"SphereRadius":69.82119}},"BodySetup":{"ObjectName":"BodySetup'TileCoverRock_FZ:BodySetup_0'","ObjectPath":"WorldExplorers/Content/World/Tiles/TileCover/Meshes/TileCoverRock_FZ.0"},"NavCollision":{"ObjectName":"NavCollision'TileCoverRock_FZ:NavCollision_0'","ObjectPath":"WorldExplorers/Content/World/Tiles/TileCover/Meshes/TileCoverRock_FZ.1"},"LightingGuid":"84A2CE73-435DAE30-3C0FCA9B-D5005818","RenderData":{"LODs":[{"Sections":[{"MaterialIndex":0,"FirstIndex":0,"NumTriangles":259,"MinVertexIndex":0,"MaxVertexIndex":157,"bEnableCollision":false,"bCastShadow":false,"bForceOpaque":false,"bVisibleInRayTracing":true}],"MaxDeviation":0.0,"PositionVertexBuffer":{"Stride":12,"NumVertices":158},"VertexBuffer":{"NumTexCoords":1,"NumVertices":158,"Strides":-1,"UseHighPrecisionTangentBasis":false,"UseFullPrecisionUVs":false},"ColorVertexBuffer":{"Stride":4,"NumVertices":158}}],"Bounds":{"Origin":{"X":-0.000030517578,"Y":0.0,"Z":-25.0},"BoxExtent":{"X":54.999985,"Y":57.27304,"Z":25.0},"SphereRadius":69.82119},"bLODsShareStaticLighting":true,"ScreenSize":[1.0,0.0,0.0,0.0,0.0,0.0,0.0,0.0]}}]