[{"Type":"SoundWave","Name":"TreasureHunter_M_Parry_02","Class":"UScriptClass'SoundWave'","Properties":{"NumChannels":1,"SampleRate":22050,"bOverrideConcurrency":true,"ConcurrencyOverrides":{"ResolutionRule":"EMaxConcurrentResolutionRule::PreventNew"},"Duration":1.5334694},"CompressedFormatData":{"OGG10000-1-1-1-1-1":{"BulkDataFlags":"BULKDATA_SingleUse | BULKDATA_ForceInlinePayload","ElementCount":10157,"SizeOnDisk":10157,"OffsetInFile":"0x31C9"}},"RawData":null,"CompressedDataGuid":"9B1E1FE8-4DFB37B5-3725F98C-470AE35A","RunningPlatformData":null}]